setup.py
ab/__init__.py
ab/ab.py
ab/ab_test.py
ab/mab.py
ab/mab_demo.py
ab/mab_test.py
ab/stats.py
ab/stats_test.py
ab/store.py
ab/store_mock.py
ab.egg-info/PKG-INFO
ab.egg-info/SOURCES.txt
ab.egg-info/dependency_links.txt
ab.egg-info/top_level.txt